setup.py
iamlogic_idm_package.egg-info/PKG-INFO
iamlogic_idm_package.egg-info/SOURCES.txt
iamlogic_idm_package.egg-info/dependency_links.txt
iamlogic_idm_package.egg-info/requires.txt
iamlogic_idm_package.egg-info/top_level.txt
idm_operation/IDM_Operation.py
idm_operation/__init__.py